compas_ifc/__init__.py
compas_ifc/__main__.py
compas_ifc/file.py
compas_ifc/model.py
compas_ifc/__old/__init__.py
compas_ifc/__old/attribute.py
compas_ifc/__old/attributes.py
compas_ifc/__old/building.py
compas_ifc/__old/buildingelements.py
compas_ifc/__old/buildingstorey.py
compas_ifc/__old/element.py
compas_ifc/__old/entity.py
compas_ifc/__old/factory.py
compas_ifc/__old/geographicelement.py
compas_ifc/__old/geometricmodel.py
compas_ifc/__old/helpers.py
compas_ifc/__old/model.py
compas_ifc/__old/objectdefinition.py
compas_ifc/__old/product.py
compas_ifc/__old/project.py
compas_ifc/__old/reader.py
compas_ifc/__old/representation.py
compas_ifc/__old/root.py
compas_ifc/__old/site.py
compas_ifc/__old/space.py
compas_ifc/__old/spatialelement.py
compas_ifc/__old/writer.py
compas_ifc/brep/__init__.py
compas_ifc/brep/ifcbrepobject.py
compas_ifc/brep/tessellatedbrep.py
compas_ifc/brep/tessellatedbrepobject.py
compas_ifc/conversions/brep.py
compas_ifc/conversions/frame.py
compas_ifc/conversions/mesh.py
compas_ifc/conversions/primitives.py
compas_ifc/conversions/pset.py
compas_ifc/conversions/representation.py
compas_ifc/conversions/shapes.py
compas_ifc/conversions/unit.py
compas_ifc/entities/__init__.py
compas_ifc/entities/base.py
compas_ifc/entities/generator.py
compas_ifc/entities/generator_enumeration_type.py
compas_ifc/entities/generator_type_definition.py
compas_ifc/entities/extensions/IfcBuilding.py
compas_ifc/entities/extensions/IfcContext.py
compas_ifc/entities/extensions/IfcElement.py
compas_ifc/entities/extensions/IfcObject.py
compas_ifc/entities/extensions/IfcObjectDefinition.py
compas_ifc/entities/extensions/IfcProduct.py
compas_ifc/entities/extensions/IfcProject.py
compas_ifc/entities/extensions/IfcSite.py
compas_ifc/entities/extensions/IfcSpatialElement.py
compas_ifc/entities/extensions/IfcSpatialStructureElement.py
compas_ifc/entities/extensions/__init__.py
compas_ifc-1.7.0.dist-info/licenses/AUTHORS.md
compas_ifc-1.7.0.dist-info/licenses/LICENSE
compas_ifc-1.7.0.dist-info/METADATA
compas_ifc-1.7.0.dist-info/WHEEL
compas_ifc-1.7.0.dist-info/top_level.txt
compas_ifc-1.7.0.dist-info/RECORD
