Metadata-Version: 2.4
Name: compas_ifc
Version: 1.7.0
Summary: High-level IFC interface for COMPAS.
Author-email: Tom Van Mele <van.mele@arch.ethz.ch>, Li Chen <li.chen@arch.ethz.ch>
License: MIT License
Project-URL: Homepage, https://github.com/compas-dev/compas_ifc
Project-URL: Documentation, https://compas.dev/compas_ifc/
Project-URL: Repository, https://github.com/compas-dev/compas_ifc.git
Project-URL: Changelog, https://github.com/compas-dev/compas_ifc/blob/main/CHANGELOG.md
Project-URL: Issues, https://github.com/compas-dev/compas_ifc/issues
Project-URL: Forum, https://forum.compas-framework.org/
Keywords: compas,ifc,bim,interoperability
Classifier: Development Status :: 5 - Production/Stable
Classifier: Topic :: Scientific/Engineering
Classifier: Operating System :: Unix
Classifier: Operating System :: POSIX
Classifier: Operating System :: Microsoft :: Windows
Classifier: Programming Language :: Python
Classifier: Programming Language :: Python :: 3
Classifier: Programming Language :: Python :: 3.9
Classifier: Programming Language :: Python :: 3.10
Classifier: Programming Language :: Python :: 3.11
Requires-Python: >=3.9
License-File: LICENSE
License-File: AUTHORS.md
Requires-Dist: compas>=2.2
Requires-Dist: ifcopenshell==0.7.0.240406
Requires-Dist: lark
Provides-Extra: dev
Requires-Dist: attrs>=17.4; extra == "dev"
Requires-Dist: black>=22.12.0; extra == "dev"
Requires-Dist: bump-my-version; extra == "dev"
Requires-Dist: compas_invocations2; extra == "dev"
Requires-Dist: invoke>=0.14; extra == "dev"
Requires-Dist: ruff; extra == "dev"
Requires-Dist: sphinx_compas2_theme; extra == "dev"
Requires-Dist: twine; extra == "dev"
Requires-Dist: wheel; extra == "dev"
Dynamic: license-file
